user_profile/CONFIG.json
user_profile/Client.py
user_profile/Profile.py
user_profile/__init__.py
user_profile/__main__.py
user_profile/Templates/default.json
kabbes_user_profile-0.11.0.dist-info/LICENSE
kabbes_user_profile-0.11.0.dist-info/METADATA
kabbes_user_profile-0.11.0.dist-info/WHEEL
kabbes_user_profile-0.11.0.dist-info/top_level.txt
kabbes_user_profile-0.11.0.dist-info/RECORD
