Metadata-Version: 2.1
Name: kabbes-user-profile
Version: 0.11.0
Summary: Universal naming system and varaible stroage for better collaboration
Home-page: https://pypi.org/project/kabbes-user-profile/
Author: James Kabbes
Author-email: james.kabbes@gmail.com
Project-URL: GitHub, https://github.com/jameskabbes/user_profile
Project-URL: Documentation, https://jameskabbes.github.io/user_profile
Classifier: Programming Language :: Python :: 3
Classifier: License :: OSI Approved :: MIT License
Classifier: Operating System :: OS Independent
Requires-Python: >=3.7
License-File: LICENSE
Requires-Dist: kabbes-py-starter
Requires-Dist: kabbes-parent-class
Requires-Dist: kabbes-dir-ops
